mcplay
