Metadata-Version: 2.1
Name: mcplay
Version: 1.0.4
Summary: Music Console Player
Home-page: https://github.com/mtatton/mcplay
Author: Michael Tatton
License: UNKNOWN
Platform: UNKNOWN
Classifier: License :: OSI Approved :: MIT License
Classifier: Operating System :: OS Independent
Classifier: Programming Language :: Python :: 3.7
Classifier: Topic :: Terminals
Requires-Python: >=3.7
License-File: LICENSE
